django_api_versioning/__init__.py
django_api_versioning/decorators.py
django_api_versioning/exceptions.py
django_api_versioning/registry.py
django_api_versioning/settings.py
django_api_versioning/urls.py
tests/__init__.py
tests/test_decorators.py
tests/test_exceptions.py
tests/test_registry.py
tests/test_settings.py
tests/test_urls.py
django_api_versioning-0.1.4.dist-info/LICENSE
django_api_versioning-0.1.4.dist-info/METADATA
django_api_versioning-0.1.4.dist-info/WHEEL
django_api_versioning-0.1.4.dist-info/top_level.txt
django_api_versioning-0.1.4.dist-info/RECORD
